watts/__init__.py
watts/console.py
watts/database.py
watts/fileutils.py
watts/fundamental_data.py
watts/mass_1.mas20.txt
watts/parameters.py
watts/plugin.py
watts/plugin_abce.py
watts/plugin_accert.py
watts/plugin_dakota.py
watts/plugin_gcmat.py
watts/plugin_mcnp.py
watts/plugin_moose.py
watts/plugin_openmc.py
watts/plugin_pyarc.py
watts/plugin_relap5.py
watts/plugin_sas.py
watts/plugin_serpent.py
watts/results.py
watts/template.py
watts-0.5.2.dist-info/entry_points.txt
watts-0.5.2.dist-info/licenses/LICENSE
watts-0.5.2.dist-info/WHEEL
watts-0.5.2.dist-info/METADATA
watts-0.5.2.dist-info/RECORD
