Metadata-Version: 2.4
Name: watts
Version: 0.5.2
Summary: Workflow and Template Toolkit for Simulation
Author-email: "UChicago Argonne, LLC" <watts@anl.gov>
Requires-Python: >=3.7
Classifier: Development Status :: 3 - Alpha
Classifier: Intended Audience :: Developers
Classifier: Intended Audience :: End Users/Desktop
Classifier: Intended Audience :: Science/Research
Classifier: License :: OSI Approved :: MIT License
Classifier: Natural Language :: English
Classifier: Operating System :: OS Independent
Classifier: Topic :: Scientific/Engineering
Classifier: Programming Language :: C++
Classifier: Programming Language :: Python :: 3
Classifier: Programming Language :: Python :: 3.7
Classifier: Programming Language :: Python :: 3.8
Classifier: Programming Language :: Python :: 3.9
Classifier: Programming Language :: Python :: 3.10
Classifier: Programming Language :: Python :: 3.11
Classifier: Programming Language :: Python :: 3.12
License-File: LICENSE
Requires-Dist: Jinja2
Requires-Dist: dill
Requires-Dist: numpy
Requires-Dist: pandas
Requires-Dist: platformdirs
Requires-Dist: prettytable
Requires-Dist: astropy
Requires-Dist: uncertainties
Requires-Dist: click
Requires-Dist: sphinx ; extra == "docs"
Requires-Dist: pydata_sphinx_theme ; extra == "docs"
Requires-Dist: sphinx_design ; extra == "docs"
Requires-Dist: sphinx-autodoc-typehints ; extra == "docs"
Requires-Dist: pytest ; extra == "test"
Project-URL: Bug Tracker, https://github.com/watts-dev/watts/issues
Project-URL: Documentation, https://watts.readthedocs.io
Project-URL: Source Code, https://github.com/watts-dev/watts
Provides-Extra: docs
Provides-Extra: test
